rollback.py
rollback-1.0.10.dist-info/LICENSE
rollback-1.0.10.dist-info/METADATA
rollback-1.0.10.dist-info/WHEEL
rollback-1.0.10.dist-info/top_level.txt
rollback-1.0.10.dist-info/RECORD
